clocky_cli/__init__.py
clocky_cli/__main__.py
clocky_cli/clocky.py
clocky_cli-2.2.dist-info/LICENSE
clocky_cli-2.2.dist-info/METADATA
clocky_cli-2.2.dist-info/WHEEL
clocky_cli-2.2.dist-info/entry_points.txt
clocky_cli-2.2.dist-info/top_level.txt
clocky_cli-2.2.dist-info/RECORD
